{"dependencies":[{"name":"/Users/matt/development/react-state-reducer/package.json","includedInParent":true,"mtime":1519427713816},{"name":"/Users/matt/development/react-state-reducer/.babelrc","includedInParent":true,"mtime":1519427604379},{"name":"/Users/matt/development/react-state-reducer/node_modules/core-js/package.json","includedInParent":true,"mtime":1513021589000}],"generated":{"js":"module.exports = '\\x09\\x0A\\x0B\\x0C\\x0D\\x20\\xA0\\u1680\\u180E\\u2000\\u2001\\u2002\\u2003' +\n  '\\u2004\\u2005\\u2006\\u2007\\u2008\\u2009\\u200A\\u202F\\u205F\\u3000\\u2028\\u2029\\uFEFF';\n","map":{"mappings":[{"source":"../node_modules/core-js/modules/_string-ws.js","original":{"line":1,"column":0},"generated":{"line":1,"column":0}},{"source":"../node_modules/core-js/modules/_string-ws.js","original":{"line":2,"column":0},"generated":{"line":2,"column":0}},{"source":"../node_modules/core-js/modules/_string-ws.js","original":{"line":3,"column":0},"generated":{"line":3,"column":0}}],"sources":{"../node_modules/core-js/modules/_string-ws.js":"module.exports = '\\x09\\x0A\\x0B\\x0C\\x0D\\x20\\xA0\\u1680\\u180E\\u2000\\u2001\\u2002\\u2003' +\n  '\\u2004\\u2005\\u2006\\u2007\\u2008\\u2009\\u200A\\u202F\\u205F\\u3000\\u2028\\u2029\\uFEFF';\n"},"lineCount":3}},"hash":"b4c4fae0e7da47c4a771aa9e6fb3bccf","cacheData":{"env":{}}}